verse/composite/script/__init__.py
verse/composite/script/component.py
verse/composite/script/providers/default.py
verse_composite-0.0.1.dist-info/LICENSE
verse_composite-0.0.1.dist-info/METADATA
verse_composite-0.0.1.dist-info/WHEEL
verse_composite-0.0.1.dist-info/RECORD
